django_configuration_management/__init__.py
django_configuration_management/aws_utils.py
django_configuration_management/cli.py
django_configuration_management/core.py
django_configuration_management/github_script.py
django_configuration_management/iam_script.py
django_configuration_management/secrets.py
django_configuration_management/utils.py
django_configuration_management/validation_utils.py
django_configuration_management/yml_utils.py
django_configuration_management-0.4.0.dist-info/entry_points.txt
django_configuration_management-0.4.0.dist-info/LICENSE
django_configuration_management-0.4.0.dist-info/WHEEL
django_configuration_management-0.4.0.dist-info/METADATA
django_configuration_management-0.4.0.dist-info/RECORD
