Metadata-Version: 2.1
Name: django-configuration-management
Version: 0.4.0
Summary: A merge conflict-less solution to committing an encrypted configuration to the repo with secrets and non-secrets side-by-side.
Home-page: https://github.com/brno32/django-configuration-management
License: MIT
Keywords: django,config,secrets,settings
Author: Alex Drozd
Author-email: drozdster@gmail.com
Requires-Python: >=3.8,<4.0
Classifier: License :: OSI Approved :: MIT License
Classifier: Programming Language :: Python :: 3
Classifier: Programming Language :: Python :: 3.8
Classifier: Programming Language :: Python :: 3.9
Requires-Dist: Django (>=4.0.3,<5.0.0)
Requires-Dist: PyGithub (>=1.54.1,<2.0.0)
Requires-Dist: PyNaCl (>=1.4.0,<2.0.0)
Requires-Dist: boto3 (>=1.17.27,<2.0.0)
Requires-Dist: cryptography (>=3.3.1,<4.0.0)
Requires-Dist: python-dotenv (>=0.15.0,<0.16.0)
Requires-Dist: pyyaml (>=5.3.1,<6.0.0)
Project-URL: Repository, https://github.com/brno32/django-configuration-management
